clserve/__init__.py
clserve/cli.py
clserve/config.py
clserve/status.py
clserve/stop.py
clserve/submit.py
clserve/configs/__init__.py
clserve/configs/models/apertus_8b.yaml
clserve/configs/models/apriel_15b_thinker.yaml
clserve/configs/models/deepseek_r1.yaml
clserve/configs/models/deepseek_v3.yaml
clserve/configs/models/deepseek_v3_2.yaml
clserve/configs/models/gpt_oss_120b.yaml
clserve/configs/models/kimi_k2.yaml
clserve/configs/models/llama_405b.yaml
clserve/configs/models/llama_70b.yaml
clserve/configs/models/llama_8b.yaml
clserve/configs/models/minimax_m2.yaml
clserve/configs/models/nemotron_nano_30b.yaml
clserve/configs/models/qwen3_235b.yaml
clserve/configs/models/qwen3_32b.yaml
clserve/configs/models/qwen3_8b.yaml
clserve/configs/models/qwen3_coder_480b.yaml
clserve/configs/models/qwen3_embedding_4b.yaml
clserve/templates/job.jinja
clserve-0.3.1.dist-info/METADATA
clserve-0.3.1.dist-info/WHEEL
clserve-0.3.1.dist-info/entry_points.txt
clserve-0.3.1.dist-info/top_level.txt
clserve-0.3.1.dist-info/RECORD
