Metadata-Version: 2.4
Name: clserve
Version: 0.3.1
Summary: CLI tool for serving LLM models on Alps
Author: Nathan Ranchin
License: MIT
Requires-Python: >=3.10
Requires-Dist: jinja2>=3.0
Requires-Dist: pyyaml>=6.0
Requires-Dist: click>=8.0
Requires-Dist: prettytable>=3.0
Requires-Dist: huggingface_hub>=0.20.0
Provides-Extra: dev
Requires-Dist: pytest>=7.0; extra == "dev"
Requires-Dist: black>=23.0; extra == "dev"
Requires-Dist: ruff>=0.1.0; extra == "dev"
